xmof/__init__.py
xmof/calculator.py
xmof-0.0.14.dist-info/METADATA
xmof-0.0.14.dist-info/WHEEL
xmof-0.0.14.dist-info/licenses/LICENSE
xmof-0.0.14.dist-info/RECORD
